cloudboot/__init__.py
cloudboot/config.py
cloudboot/consts.py
cloudboot/enum/CloudService.py
cloudboot/enum/CloudServiceRuntime.py
cloudboot/enum/CloudServiceTrigger.py
cloudboot/enum/ColorCode.py
cloudboot/enum/__init__.py
cloudboot/inquiry/__init__.py
cloudboot/inquiry/auth.py
cloudboot/inquiry/cloud_functions.py
cloudboot/inquiry/project.py
cloudboot/model/Base.py
cloudboot/model/CloudFunctionConfig.py
cloudboot/model/DataMap.py
cloudboot/model/Template.py
cloudboot/model/__init__.py
cloudboot/service/__init__.py
cloudboot/service/core/__init__.py
cloudboot/service/core/config.py
cloudboot/service/core/template.py
cloudboot/service/gcloud/__init__.py
cloudboot/service/gcloud/auth.py
cloudboot/service/gcloud/cloud_functions.py
cloudboot/service/gcloud/firestore.py
cloudboot/service/gcloud/project.py
cloudboot/service/gcloud/pubsub.py
cloudboot/service/gcloud/storage.py
cloudboot/utility/__init__.py
cloudboot/utility/downloader.py
cloudboot/utility/executor.py
cloudboot/utility/file_manager.py
cloudboot/utility/object_mapper.py
cloudboot/utility/store.py
cloudboot-0.1.0b0.data/scripts/cloudboot
cloudboot-0.1.0b0.dist-info/LICENSE
cloudboot-0.1.0b0.dist-info/METADATA
cloudboot-0.1.0b0.dist-info/WHEEL
cloudboot-0.1.0b0.dist-info/top_level.txt
cloudboot-0.1.0b0.dist-info/RECORD
